falcon_require_https/__init__.py
falcon_require_https/middleware.py
falcon_require_https/version.py
falcon_require_https-0.1.0.dist-info/DESCRIPTION.rst
falcon_require_https-0.1.0.dist-info/METADATA
falcon_require_https-0.1.0.dist-info/RECORD
falcon_require_https-0.1.0.dist-info/WHEEL
falcon_require_https-0.1.0.dist-info/metadata.json
falcon_require_https-0.1.0.dist-info/top_level.txt
